distracted_driver_detection/DistractedDriverDetection_Utils.py
distracted_driver_detection/__init__.py
Distracted_Driver_Detection-0.0.3.dist-info/LICENCE
Distracted_Driver_Detection-0.0.3.dist-info/METADATA
Distracted_Driver_Detection-0.0.3.dist-info/WHEEL
Distracted_Driver_Detection-0.0.3.dist-info/top_level.txt
Distracted_Driver_Detection-0.0.3.dist-info/RECORD
