Metadata-Version: 2.1
Name: Distracted Driver Detection
Version: 0.0.3
Summary: Distracted Driver Detection Project
Home-page: https://github.com/MohamedSebaie/Distracted_Driver_Detection_Project
Author: Mohamed Sebaie
Author-email: mohamedsebaie1@gmail.com
License: UNKNOWN
Platform: UNKNOWN
Classifier: Programming Language :: Python :: 3
Classifier: License :: OSI Approved :: MIT License
Classifier: Operating System :: OS Independent
Requires-Python: >=3.7
License-File: LICENCE
